chinese_restauraunt_process-0.2.0.dist-info/licenses/LICENSE
crp/__init__.py
crp/process.py
crp/table.py
chinese_restauraunt_process-0.2.0.dist-info/METADATA
chinese_restauraunt_process-0.2.0.dist-info/WHEEL
chinese_restauraunt_process-0.2.0.dist-info/top_level.txt
chinese_restauraunt_process-0.2.0.dist-info/RECORD
