Metadata-Version: 2.4
Name: chinese_restauraunt_process
Version: 0.2.0
Summary: Chinese Restaurant Processes in Python
Author-email: James Haberberger <jhaberbe@stanford.edu>
License-File: LICENSE
Requires-Dist: ipykernel>=6.29.5
Requires-Dist: numpy
Requires-Dist: scipy
Requires-Dist: tqdm
Dynamic: license-file
